{
  "recentFiles": [
    {
      "basename": "WEB_daily",
      "path": "Daily/WEB_daily.md"
    },
    {
      "basename": "数据库_daily",
      "path": "Daily/数据库_daily.md"
    },
    {
      "basename": "2023下半年",
      "path": "Daily/2023下半年.md"
    },
    {
      "basename": "2023日记",
      "path": "Daily/2023日记.md"
    },
    {
      "basename": "Android_note",
      "path": "Daily/Android_note.md"
    },
    {
      "basename": "_Index_of_Daily",
      "path": "Daily/_Index_of_Daily.md"
    },
    {
      "basename": "0_daily2023",
      "path": "0_Xiaoli/0_daily2023.md"
    },
    {
      "basename": "a_daily2022",
      "path": "0_Xiaoli/a_daily2022.md"
    },
    {
      "basename": "2022日记",
      "path": "0_Xiaoli/2022日记.md"
    },
    {
      "basename": "c++基础",
      "path": "2023下半/c++游戏ll项目/c++基础.md"
    },
    {
      "basename": "daily",
      "path": "2023下半/数据库/daily.md"
    },
    {
      "basename": "Django",
      "path": "notebook/Django.md"
    },
    {
      "basename": "Android_note",
      "path": "Daily/移动应用开发/Android_note.md"
    },
    {
      "basename": "tool网站",
      "path": "0重要!待完成/tool网站.md"
    },
    {
      "basename": "GO_学习",
      "path": "Daily/GO_学习.md"
    },
    {
      "basename": "100",
      "path": "100.md"
    },
    {
      "basename": "未命名",
      "path": "未命名.canvas"
    },
    {
      "basename": "README",
      "path": "README.md"
    },
    {
      "basename": "2023-09-22",
      "path": "2023-09-22.md"
    },
    {
      "basename": "2023-09-23",
      "path": "2023-09-23.md"
    },
    {
      "basename": "java",
      "path": "notebook/java相关/java.md"
    },
    {
      "basename": "素材绘制",
      "path": "游戏背景资料/素材绘制.md"
    },
    {
      "basename": "项目计划",
      "path": "游戏背景资料/项目计划.md"
    },
    {
      "basename": "小tips",
      "path": "algorithms/小tips.md"
    },
    {
      "basename": "record",
      "path": "2023下半/Web/record.md"
    },
    {
      "basename": "Record",
      "path": "2023下半/Record.md"
    },
    {
      "basename": "os习题",
      "path": "notebook/os习题.pdf"
    },
    {
      "basename": "_Index_of_Typora_my",
      "path": "_Index_of_Typora_my.md"
    },
    {
      "basename": "_Index_of_移动应用开发",
      "path": "Daily/移动应用开发/_Index_of_移动应用开发.md"
    },
    {
      "basename": "初三化学",
      "path": "0重要!待完成/初三化学.md"
    },
    {
      "basename": "E-P1097",
      "path": "algorithms/错题/2022/10.21/E-P1097.md"
    },
    {
      "basename": "2022日记",
      "path": "Daily/2022日记.md"
    },
    {
      "basename": "_Index_of_0_Xiaoli",
      "path": "0_Xiaoli/_Index_of_0_Xiaoli.md"
    },
    {
      "basename": "添加元素到列表末尾",
      "path": "添加元素到列表末尾.md"
    },
    {
      "basename": "p1018",
      "path": "p1018.pdf"
    },
    {
      "basename": "Python流水代码",
      "path": "notebook/Python流水代码.md"
    }
  ],
  "omittedPaths": [],
  "maxLength": null,
  "openType": "tab"
}